aiostp/__init__.py
aiostp/auth.py
aiostp/exc.py
aiostp/utils.py
aiostp/version.py
aiostp/http/__init__.py
aiostp/http/client.py
aiostp/resources/__init__.py
aiostp/resources/base.py
aiostp/resources/ordenes.py
aiostp/resources/saldos.py
tests/__init__.py
tests/test_auth.py
tests/test_utils.py
tests/http/__init__.py
tests/http/test_client.py
tests/resources/__init__.py
tests/resources/conftest.py
tests/resources/test_base.py
tests/resources/test_ordenes.py
tests/resources/test_saldos.py
aiostp-0.0.12.dist-info/LICENSE
aiostp-0.0.12.dist-info/METADATA
aiostp-0.0.12.dist-info/WHEEL
aiostp-0.0.12.dist-info/top_level.txt
aiostp-0.0.12.dist-info/RECORD
