Metadata-Version: 2.1
Name: aiostp
Version: 0.0.12
Summary: asyncio client library for stpmex.com
Home-page: https://github.com/cuenca-mx/aiostp
Author: Cuenca
Author-email: dev@cuenca.com
Classifier: Programming Language :: Python :: 3
Classifier: Programming Language :: Python :: 3.7
Classifier: Programming Language :: Python :: 3.8
Classifier: License :: OSI Approved :: MIT License
Classifier: Operating System :: OS Independent
Requires-Python: >=3.7
License-File: LICENSE
Requires-Dist: aiohttp (<3.9.0,>=3.7.3)
Requires-Dist: cryptography (<40.1,>=3.0)
Requires-Dist: cuenca-validations (<0.12.0,>=0.5.0)
Requires-Dist: aiofile (<3.8.0,>=3.7.0)
Requires-Dist: pydantic (<1.10.0,>=1.7.0)
Requires-Dist: pandas (<1.5.0,>=1.1.0)
Requires-Dist: stpmex (<3.12.0,>=3.6.0)
